dictppr/__init__.py
dictppr/dictppr.py
dictppr-1.0.0.dist-info/LICENSE
dictppr-1.0.0.dist-info/METADATA
dictppr-1.0.0.dist-info/WHEEL
dictppr-1.0.0.dist-info/top_level.txt
dictppr-1.0.0.dist-info/RECORD
