Metadata-Version: 2.1
Name: dictppr
Version: 1.0.0
Summary: Python library for easy-to-read conversion of a dictionary to a string and pretty printing.
Home-page: https://github.com/TheFifthLeaf/dictppr
Download-URL: https://github.com/TheFifthLeaf/dictppr/archive/refs/tags/v1.0.0.zip
Author: Dawid Jach
Author-email: jach.developer@protonmail.com
License: GNU GPLv3
Project-URL: pypi, https://pypi.org/project/dictppr/
Keywords: python,dict,dictionary,str,string,pretty,print,printing,converter
Platform: UNKNOWN
Classifier: Development Status :: 3 - Alpha
Classifier: Intended Audience :: Developers
Classifier: Topic :: Software Development :: Build Tools
Classifier: License :: OSI Approved :: GNU General Public License v3 (GPLv3)
Classifier: Natural Language :: English
Classifier: Programming Language :: Python :: 3.6
Classifier: Programming Language :: Python :: 3.7
Classifier: Programming Language :: Python :: 3.8
Classifier: Programming Language :: Python :: 3.9
Classifier: Programming Language :: Python :: 3.10
Classifier: Operating System :: POSIX :: Linux
Classifier: Operating System :: MacOS :: MacOS X
Classifier: Operating System :: Microsoft :: Windows
Requires-Python: >=3.6
License-File: LICENSE
